MANIFEST.in
README
__init__.py
__pkginfo__.py
calendars.py
hooks.py
schema.py
setup.py
uiprops.py
utils.py
cubicweb_timeseries.egg-info/PKG-INFO
cubicweb_timeseries.egg-info/SOURCES.txt
cubicweb_timeseries.egg-info/dependency_links.txt
cubicweb_timeseries.egg-info/not-zip-safe
cubicweb_timeseries.egg-info/requires.txt
cubicweb_timeseries.egg-info/top_level.txt
data/cubes.timeseries.css
data/cubes.timeseries.js
data/grid.locale-en.js
data/jquery-ui-1.7.2.custom.css
data/jquery.flot.selection.js
data/jquery.jqGrid.js
data/jquery.sparkline.js
data/ui.jqgrid.css
data/images/ui-bg_flat_0_aaaaaa_40x100.png
data/images/ui-bg_flat_75_ffffff_40x100.png
data/images/ui-bg_glass_55_fbf9ee_1x400.png
data/images/ui-bg_glass_65_ffffff_1x400.png
data/images/ui-bg_glass_75_dadada_1x400.png
data/images/ui-bg_glass_75_e6e6e6_1x400.png
data/images/ui-bg_glass_95_fef1ec_1x400.png
data/images/ui-bg_highlight-soft_75_cccccc_1x100.png
data/images/ui-icons_222222_256x240.png
data/images/ui-icons_2e83ff_256x240.png
data/images/ui-icons_454545_256x240.png
data/images/ui-icons_888888_256x240.png
data/images/ui-icons_cd0a0a_256x240.png
entities/__init__.py
entities/abstract.py
entities/adapters.py
entities/nonperiodic.py
entities/timeseries.py
entities/utils.py
i18n/en.po
i18n/es.po
i18n/fr.po
migration/0.10.0_Any.py
migration/0.10.3_Any.py
migration/0.13.0_Any.py
migration/0.13.1_Any.py
migration/0.15.0_Any.py
migration/1.0.0._Any.py
migration/1.1.0_Any.py
migration/1.4.0_Any.py
migration/postcreate.py
migration/precreate.py
test/unittest_calendar.py
test/unittest_excel_preferences.py
test/unittest_io.py
test/unittest_timeseries.py
views/__init__.py
views/export.py
views/formwidgets.py
views/incontext.py
views/plot.py
views/primary.py
views/sparkline.py