Metadata-Version: 1.0
Name: cubicweb-timeseries
Version: 1.5.0
Summary: timeseries component for the CubicWeb framework
Home-page: http://www.cubicweb.org/project/cubicweb-timeseries
Author: LOGILAB S.A. (Paris, FRANCE)
Author-email: contact@logilab.fr
License: LCL
Platform: UNKNOWN
